hipporag_lite/HippoRAG.py
hipporag_lite/StandardRAG.py
hipporag_lite/__init__.py
hipporag_lite/embedding_model/Qwen3.py
hipporag_lite/embedding_model/__init__.py
hipporag_lite/embedding_model/base.py
hipporag_lite/embedding_store.py
hipporag_lite/evaluation/README.md
hipporag_lite/evaluation/__init__.py
hipporag_lite/evaluation/base.py
hipporag_lite/evaluation/qa_eval.py
hipporag_lite/evaluation/retrieval_eval.py
hipporag_lite/information_extraction/__init__.py
hipporag_lite/information_extraction/openie_openai.py
hipporag_lite/llm/__init__.py
hipporag_lite/llm/base.py
hipporag_lite/llm/request_llm.py
hipporag_lite/prompts/__init__.py
hipporag_lite/prompts/dspy_prompts/filter_llama3.3-70B-Instruct.json
hipporag_lite/prompts/filter_default_prompt.py
hipporag_lite/prompts/linking.py
hipporag_lite/prompts/prompt_template_manager.py
hipporag_lite/prompts/templates/README.md
hipporag_lite/prompts/templates/__init__.py
hipporag_lite/prompts/templates/ircot_hotpotqa.py
hipporag_lite/prompts/templates/ircot_musique.py
hipporag_lite/prompts/templates/ner.py
hipporag_lite/prompts/templates/ner_query.py
hipporag_lite/prompts/templates/rag_qa_musique.py
hipporag_lite/prompts/templates/triple_extraction.py
hipporag_lite/rerank.py
hipporag_lite/utils/__init__.py
hipporag_lite/utils/config_utils.py
hipporag_lite/utils/embed_utils.py
hipporag_lite/utils/eval_utils.py
hipporag_lite/utils/llm_utils.py
hipporag_lite/utils/logging_utils.py
hipporag_lite/utils/misc_utils.py
hipporag_lite/utils/qa_utils.py
hipporag_lite/utils/typing.py
hipporag_lite-0.1.1.dist-info/LICENSE
hipporag_lite-0.1.1.dist-info/METADATA
hipporag_lite-0.1.1.dist-info/WHEEL
hipporag_lite-0.1.1.dist-info/RECORD
