Metadata-Version: 2.3
Name: HippoRAG-Lite
Version: 0.1.1
Summary: (v0.1.0: 异步化三大常用函数，增加三条数据结构常有函数)去除了HippoRAG2中的torch，vllm，甚至openai；完全由siliconflow api和本地cpu实现功能。
License: MIT
Author: inkink365
Author-email: inkink365@outlook.com
Requires-Python: >=3.10,<4.0
Classifier: License :: OSI Approved :: MIT License
Classifier: Programming Language :: Python :: 3
Classifier: Programming Language :: Python :: 3.10
Classifier: Programming Language :: Python :: 3.11
Classifier: Programming Language :: Python :: 3.12
Classifier: Programming Language :: Python :: 3.13
Requires-Dist: filelock (==3.16.1)
Requires-Dist: numpy (==1.26.4)
Requires-Dist: pandas (==2.3.1)
Requires-Dist: pyarrow (==21.0.0)
Requires-Dist: pydantic (==2.10.4)
Requires-Dist: python_igraph (==0.11.8)
Requires-Dist: requests (>=2.28.0)
Requires-Dist: tenacity (==8.5.0)
Requires-Dist: tqdm
Project-URL: Repository, https://github.com/inkink365/HippoRAG-Lite
